.DS_Store
audio_searcher/__init__.py
audio_searcher/audio_search.py
audio_searcher-0.1.3.dist-info/LICENSE
audio_searcher-0.1.3.dist-info/METADATA
audio_searcher-0.1.3.dist-info/WHEEL
audio_searcher-0.1.3.dist-info/entry_points.txt
audio_searcher-0.1.3.dist-info/top_level.txt
audio_searcher-0.1.3.dist-info/RECORD
