Metadata-Version: 2.1
Name: audio-searcher
Version: 0.1.3
Summary: A tool to search for keywords in audio files
Home-page: https://github.com/kinmedwuai/audio_searcher
Author: myun
Author-email: s2222030@stu.musashino-u.ac.jp
License: UNKNOWN
Platform: UNKNOWN
Classifier: Programming Language :: Python :: 3
Classifier: License :: OSI Approved :: MIT License
Classifier: Operating System :: OS Independent
Requires-Python: >=3.6
License-File: LICENSE
Requires-Dist: SpeechRecognition
Requires-Dist: pydub
